aext_assistant_server/__init__.py
aext_assistant_server-0.0.1.dist-info/METADATA
aext_assistant_server-0.0.1.dist-info/WHEEL
aext_assistant_server-0.0.1.dist-info/RECORD
