Metadata-Version: 2.1
Name: aext-assistant-server
Version: 0.0.1
Summary: The aext-assistant-server component of anaconda-toolbox
License-Expression: BSD-3-Clause
